clusterimg/Clusteror.py
clusterimg/DL_Clusteror.py
clusterimg/DL_Datasets.py
clusterimg/DL_ModelTrainer.py
clusterimg/DL_Models.py
clusterimg/DL_clusterimg_test.py
clusterimg/__init__.py
clusterimg/clusterimg_test.py
clusterimg/global_variables.py
clusterimg/helper_exceptions.py
clusterimg/helper_functions.py
segmentimg/GrabcutSegmentator.py
segmentimg/SAMSegmentator.py
segmentimg/Segmentator.py
segmentimg/__init__.py
segmentimg/helper_exceptions.py
segmentimg/helper_functions.py
segmentimg/segmentimg_test.py
icas-1.1.dist-info/METADATA
icas-1.1.dist-info/NOTICE.txt
icas-1.1.dist-info/WHEEL
icas-1.1.dist-info/top_level.txt
icas-1.1.dist-info/RECORD
