Metadata-Version: 2.1
Name: icas
Version: 1.1
Summary: Tool for labeling images
Home-page: https://github.com/mericdemirors/icas
Author: mericdemirors
Author-email: demirorsmeric@gmail.com
License: UNKNOWN
Platform: UNKNOWN
License-File: NOTICE.txt
Requires-Dist: ImageHash >=4.3.1
Requires-Dist: Pillow >=10.3.0
Requires-Dist: datasketch >=1.6.4
Requires-Dist: matplotlib >=3.8.4
Requires-Dist: mplcursors >=0.5.3
Requires-Dist: numpy >=1.26.4
Requires-Dist: opencv-contrib-python >=4.9.0.80
Requires-Dist: scikit-image >=0.22.0
Requires-Dist: tqdm >=4.66.2
